GoogleKaiyuanXiangmuFenggeZhinan/README.md
GoogleKaiyuanXiangmuFenggeZhinan/__init__.py
GoogleKaiyuanXiangmuFenggeZhinan/__main__.py
GoogleKaiyuanXiangmuFenggeZhinan/file.epub
GoogleKaiyuanXiangmuFenggeZhinan/index.html
GoogleKaiyuanXiangmuFenggeZhinan/css/__init__.py
GoogleKaiyuanXiangmuFenggeZhinan/css/annotations.css
GoogleKaiyuanXiangmuFenggeZhinan/css/main.css
GoogleKaiyuanXiangmuFenggeZhinan/css/normalize.css
GoogleKaiyuanXiangmuFenggeZhinan/css/popup.css
GoogleKaiyuanXiangmuFenggeZhinan/font/__init__.py
GoogleKaiyuanXiangmuFenggeZhinan/font/fontello.eot
GoogleKaiyuanXiangmuFenggeZhinan/font/fontello.svg
GoogleKaiyuanXiangmuFenggeZhinan/font/fontello.ttf
GoogleKaiyuanXiangmuFenggeZhinan/font/fontello.woff
GoogleKaiyuanXiangmuFenggeZhinan/img/__init__.py
GoogleKaiyuanXiangmuFenggeZhinan/img/annotator-glyph-sprite.png
GoogleKaiyuanXiangmuFenggeZhinan/img/annotator-icon-sprite.png
GoogleKaiyuanXiangmuFenggeZhinan/img/apple-touch-icon.png
GoogleKaiyuanXiangmuFenggeZhinan/img/cancelfullscreen.png
GoogleKaiyuanXiangmuFenggeZhinan/img/close.png
GoogleKaiyuanXiangmuFenggeZhinan/img/fullscreen.png
GoogleKaiyuanXiangmuFenggeZhinan/img/loader.gif
GoogleKaiyuanXiangmuFenggeZhinan/img/menu-icon.png
GoogleKaiyuanXiangmuFenggeZhinan/img/save.png
GoogleKaiyuanXiangmuFenggeZhinan/img/saved.png
GoogleKaiyuanXiangmuFenggeZhinan/img/settings-s.png
GoogleKaiyuanXiangmuFenggeZhinan/img/settings.png
GoogleKaiyuanXiangmuFenggeZhinan/img/star.png
GoogleKaiyuanXiangmuFenggeZhinan/js/__init__.py
GoogleKaiyuanXiangmuFenggeZhinan/js/epub.js
GoogleKaiyuanXiangmuFenggeZhinan/js/epub.min.js
GoogleKaiyuanXiangmuFenggeZhinan/js/epub.min.map
GoogleKaiyuanXiangmuFenggeZhinan/js/hooks.min.js
GoogleKaiyuanXiangmuFenggeZhinan/js/hooks.min.map
GoogleKaiyuanXiangmuFenggeZhinan/js/reader.js
GoogleKaiyuanXiangmuFenggeZhinan/js/reader.js.map
GoogleKaiyuanXiangmuFenggeZhinan/js/reader.min.js
GoogleKaiyuanXiangmuFenggeZhinan/js/reader.min.map
GoogleKaiyuanXiangmuFenggeZhinan/js/hooks/__init__.py
google_kaiyuan_xiangmu_fengge_zhinan-2024.3.1.0.dist-info/METADATA
google_kaiyuan_xiangmu_fengge_zhinan-2024.3.1.0.dist-info/WHEEL
google_kaiyuan_xiangmu_fengge_zhinan-2024.3.1.0.dist-info/entry_points.txt
google_kaiyuan_xiangmu_fengge_zhinan-2024.3.1.0.dist-info/top_level.txt
google_kaiyuan_xiangmu_fengge_zhinan-2024.3.1.0.dist-info/RECORD
